{
    "Ar36": {
        "error": 0.0235851343612733, 
        "fit": "parabolic", 
        "value": 3.6224854016485644
    }, 
    "Ar37": {
        "error": 0.13757561249124303, 
        "fit": "linear", 
        "value": -0.074276474601964571
    }, 
    "Ar38": {
        "error": 0.11355097184365512, 
        "fit": "linear", 
        "value": 0.60665289352529084
    }, 
    "Ar39": {
        "error": 0.059655043318337084, 
        "fit": "parabolic", 
        "value": 0.014222966132747566
    }, 
    "Ar40": {
        "error": 0.38981271766958098, 
        "fit": "parabolic", 
        "value": 1101.9989785669545
    }, 
    "Ar41": {
        "error": 0.11667988159368668, 
        "fit": "average_SEM", 
        "value": -0.028853857309877641
    }
}