{
    "Ar36": {
        "error": 0.0078869458884684406, 
        "fit": "parabolic", 
        "value": 0.4031799109843105
    }, 
    "Ar37": {
        "error": 0.13845218601285247, 
        "fit": "linear", 
        "value": 7.5454565342589799
    }, 
    "Ar38": {
        "error": 0.11028798625764333, 
        "fit": "linear", 
        "value": 0.38392337913300217
    }, 
    "Ar39": {
        "error": 0.07696947339481959, 
        "fit": "parabolic", 
        "value": 21.979025990736243
    }, 
    "Ar40": {
        "error": 0.16783323779064632, 
        "fit": "parabolic", 
        "value": 122.94405808746305
    }, 
    "Ar41": {
        "error": 0.11578988538448295, 
        "fit": "average_SEM", 
        "value": -0.012031647262192564
    }
}