{
    "AX": {
        "error": 0.05694487142339941, 
        "fit": "average_SEM", 
        "value": -0.01351285603401872
    }, 
    "CDD": {
        "error": 4.925647171999462e-05, 
        "fit": "average_SEM", 
        "value": 5.602497397679447e-06
    }, 
    "H1": {
        "error": 0.11881222210041598, 
        "fit": "average_SEM", 
        "value": -0.004050324408065838
    }, 
    "H2": {
        "error": 0.12070892928220359, 
        "fit": "average_SEM", 
        "value": -0.012194900027437446
    }, 
    "L1": {
        "error": 0.11078174205530628, 
        "fit": "average_SEM", 
        "value": -0.05932709840320361
    }, 
    "L2": {
        "error": 0.12712001528330522, 
        "fit": "average_SEM", 
        "value": -0.03131031616794644
    }
}