{
    "AX": {
        "error": 0.06024339111809138, 
        "fit": "average_SEM", 
        "value": -0.01668265384220528
    }, 
    "CDD": {
        "error": 3.5961234415936156e-05, 
        "fit": "average_SEM", 
        "value": -3.310571158484284e-06
    }, 
    "H1": {
        "error": 0.11463439990021046, 
        "fit": "average_SEM", 
        "value": -0.0038426875767375653
    }, 
    "H2": {
        "error": 0.11980416898143818, 
        "fit": "average_SEM", 
        "value": -0.03132622266712133
    }, 
    "L1": {
        "error": 0.11120080722137272, 
        "fit": "average_SEM", 
        "value": -0.087574528780533
    }, 
    "L2": {
        "error": 0.1273711457404934, 
        "fit": "average_SEM", 
        "value": -0.06595170306585109
    }
}