{
    "AX": {
        "error": 0.050440084515218656, 
        "fit": "average_SEM", 
        "value": 0.023756216232626078
    }, 
    "CDD": {
        "error": 8.690951611144536e-05, 
        "fit": "average_SEM", 
        "value": 3.8198864785954356e-05
    }, 
    "H1": {
        "error": 0.10766076333734625, 
        "fit": "average_SEM", 
        "value": -0.6120776690542697
    }, 
    "H2": {
        "error": 0.1108184249020697, 
        "fit": "average_SEM", 
        "value": -0.4536412075161934
    }, 
    "L1": {
        "error": 0.09939236569971484, 
        "fit": "average_SEM", 
        "value": -0.49865100731452305
    }, 
    "L2": {
        "error": 0.2565228638058478, 
        "fit": "average_SEM", 
        "value": -0.5326858576542387
    }
}