{
    "AX": {
        "error": 0.052447961119950745, 
        "fit": "average_SEM", 
        "value": -0.013690377395414543
    }, 
    "CDD": {
        "error": 0.00020930583808486725, 
        "fit": "average_SEM", 
        "value": 0.0002704479643701537
    }, 
    "H1": {
        "error": 0.11000693951721745, 
        "fit": "average_SEM", 
        "value": 0.009513325993975742
    }, 
    "H2": {
        "error": 0.11567606824283273, 
        "fit": "average_SEM", 
        "value": -0.024513142223198277
    }, 
    "L1": {
        "error": 0.11308616012330756, 
        "fit": "average_SEM", 
        "value": -0.08880965414718958
    }, 
    "L2": {
        "error": 0.1355652715531167, 
        "fit": "average_SEM", 
        "value": -0.019455902501552675
    }
}