{
    "Ar36": {
        "error": 0.026381583902516714, 
        "fit": "parabolic", 
        "value": 4.4232187301405279
    }, 
    "Ar37": {
        "error": 0.26467894128582914, 
        "fit": "linear", 
        "value": -0.4517482582465242
    }, 
    "Ar38": {
        "error": 0.11887064504328557, 
        "fit": "linear", 
        "value": 0.38739325911569211
    }, 
    "Ar39": {
        "error": 0.059447479039368818, 
        "fit": "parabolic", 
        "value": 0.048115124485156049
    }, 
    "Ar40": {
        "error": 0.44329033112873006, 
        "fit": "parabolic", 
        "value": 1335.3853923296488
    }, 
    "Ar41": {
        "error": 0.11706914069242082, 
        "fit": "average_SEM", 
        "value": -0.42583771641366186
    }
}